{
  "Users": [
    {
      "firstName": "viraj",
      "lastName": "kale",
      "email": "viraj@gmail.com",
      "contact": "9876543210",
      "address": "Pune",
      "username": "viraj",
      "password": "123",
      "id": 1,
      "savedProductsList": []
    },
    {
      "firstName": "manas",
      "lastName": "kirad",
      "email": "manas@gmail.com",
      "contact": "9876543210",
      "address": "Pune",
      "username": "manas",
      "password": "123",
      "id": 2,
      "savedProductsList": []
    }
  ],
  "Products": [
    {
      "id": 1,
      "productName": "car",
      "productCategory": "Cars",
      "productDescription": "this is a car",
      "productImage": "../../../assets/images/car1.jpg",
      "productPrice": "$4000",
      "savedProduct": false
    },
    {
      "id": 2,
      "productName": "car",
      "productCategory": "Cars",
      "productDescription": "this is a car",
      "productImage": "../../../assets/images/car2.jpg",
      "productPrice": "$5000",
      "savedProduct": false
    },
    {
      "id": 3,
      "productName": "bike",
      "productCategory": "Bikes",
      "productDescription": "this is a bike",
      "productImage": "../../../assets/images/bike1.jpg",
      "productPrice": "$2000",
      "savedProduct": false
    },
    {
      "id": 4,
      "productName": "bike",
      "productCategory": "Bikes",
      "productDescription": "this is a bike",
      "productImage": "../../../assets/images/bike1.jpg",
      "productPrice": "$2000",
      "savedProduct": false
    }
  ]
}